{
  "name": "ChainLightning_Jump2",
  "display_name": "ChainLightning_Jump2",
  "display_fullname": "TalonsOfVengeance.ChainLightning Jump2",
  "display_help": "Talons of Vengeance",
  "display_short_help": "Talons of Vengeance",
  "available_level": [
    0
  ],
  "source_file": "DEFS/POWERS/TALONSOFVENGEANCE/CHAINLIGHTNING_JUMP2.POWERSETS",
  "icon": "chainlightning_jump2_set.png",
  "requires": "",
  "power_names": [
    "TalonsOfVengeance.ChainLightning_Jump2.Charge"
  ],
  "power_display_names": [
    "Charge"
  ],
  "power_short_helps": [
    "Charged"
  ]
}
