{
  "name": "Crafted_Luck_of_the_Gambler_C",
  "display_name": "Crafted Luck of the Gambler C",
  "display_fullname": "Boosts.Crafted Luck of the Gambler C",
  "display_help": "Reduces the recharge time of a power by {Boost.Attrib.RechargeTime.Scale}% and reduces endurance cost by {Boost.Attrib.Endurance.Scale}%.",
  "display_short_help": "Set: Luck of the Gambler",
  "available_level": [
    0
  ],
  "source_file": "DEFS/POWERS/BOOSTS/CRAFTED_LUCK_OF_THE_GAMBLER_C.POWERSETS",
  "icon": "crafted_luck_of_the_gambler_c_set.png",
  "requires": "",
  "power_names": [
    "Boosts.Crafted_Luck_of_the_Gambler_C.Crafted_Luck_of_the_Gambler_C"
  ],
  "power_display_names": [
    "Luck of the Gambler: Endurance/Recharge"
  ],
  "power_short_helps": [
    "Reduces Endurance Cost and Increases Attack Rate"
  ]
}
