{
  "name": "Attuned_Edict_of_the_Master_D",
  "display_name": "Attuned Edict of the Master D",
  "display_fullname": "Boosts.Attuned Edict of the Master D",
  "display_help": "Enhances the accuracy of a power by {Boost.Attrib.Accuracy.Scale}% and damage by {Boost.Attrib.Damage.Scale}% and reduces endurance cost by {Boost.Attrib.Endurance.Scale}%.",
  "display_short_help": "Set: Edict of the Master",
  "available_level": [
    0
  ],
  "source_file": "DEFS/POWERS/BOOSTS/ATTUNED_EDICT_OF_THE_MASTER_D.POWERSETS",
  "icon": "attuned_edict_of_the_master_d_set.png",
  "requires": "",
  "power_names": [
    "Boosts.Attuned_Edict_of_the_Master_D.Attuned_Edict_of_the_Master_D"
  ],
  "power_display_names": [
    "Edict of the Master: Accuracy/Damage/Endurance"
  ],
  "power_short_helps": [
    "Enhances Damage, Reduces Endurance Cost and Increases Accuracy"
  ]
}
