{
  "name": "BlackKnights_Dread_Templar",
  "gender": "GENDER_MALE",
  "group_name": "BlackKnights",
  "commandable_pet": 0,
  "power_tags": [
    "HumanSkeleton",
    "Human",
    "Undead"
  ],
  "ally": null,
  "gang": null,
  "game_exclusion": "None",
  "inactive_state_weapon": null,
  "copy_creator_mods": false,
  "can_zone": false,
  "custom_badge_stat": null,
  "badge_stat_flags": "DefaultBadgeStat",
  "defaults": {
    "min_level": 25,
    "max_level": 55,
    "requires": "",
    "spawn_limit": -1,
    "spawn_limit_mission": -1,
    "ignore_combat_mods": false,
    "ignore_av_to_eb_scaling": false,
    "rank": "VR_BOSS",
    "ai_config": "BanishedPantheon_Spirit_of_Pain",
    "character_class_name": "boss_grunt",
    "description": "The Black Knights are an ancient Order of the dead that is charged with overseeing the Eternal Prison; a place where only the wickedest of souls are jailed. Captains of the Eternal Order, the Dread Templars are amongst the oldest and most renowned of the knightly order. Few possess the dedication to become a Templar, but those that do are blessed with immense strength and resilience. Driven by their mighty oaths to the order, a Dread Templar will stop at nothing to vanquish their enemies.",
    "group_description": null,
    "display_class_name": null,
    "display_name": null,
    "costume": null,
    "reward_scale": 1.0,
    "additional_rewards": [],
    "power_full_names": [
      "BlackKnights.Broad_Sword.Hack",
      "BlackKnights.Broad_Sword.Slash",
      "BlackKnights.Broad_Sword.Nether_Blade",
      "BlackKnights.Broad_Sword.Slice",
      "BlackKnights.Broad_Sword.Whirling_Sword",
      "BlackKnights.Broad_Sword.Head_Splitter",
      "BlackKnights.Shield_Defense.Deflection",
      "BlackKnights.Shield_Defense.Phalanx_Fighting",
      "BlackKnights.Shield_Defense.Active_Defense",
      "BlackKnights.Resistances.Damage_BS"
    ],
    "power_display_names": [
      "Hack",
      "Slash",
      "Nether Blade",
      "Slice",
      "Whirling Sword",
      "Head Splitter",
      "Deflection",
      "Phalanx Fighting",
      "Active Defense",
      "Damage Resistance"
    ],
    "power_levels": [
      0,
      0,
      0,
      0,
      0,
      0,
      0,
      0,
      0,
      0
    ],
    "is_dynamic": false,
    "powers": [
      {
        "power_category": "BlackKnights",
        "power_set": "Broad_Sword",
        "power": "*",
        "level": 0
      },
      {
        "power_category": "BlackKnights",
        "power_set": "Shield_Defense",
        "power": "Deflection",
        "level": 0
      },
      {
        "power_category": "BlackKnights",
        "power_set": "Shield_Defense",
        "power": "Phalanx_Fighting",
        "level": 0
      },
      {
        "power_category": "BlackKnights",
        "power_set": "Shield_Defense",
        "power": "Active_Defense",
        "level": 0
      },
      {
        "power_category": "BlackKnights",
        "power_set": "Resistances",
        "power": "Damage_BS",
        "level": 0
      }
    ],
    "condition_hash": null
  },
  "conditions": [],
  "levels": [
    {
      "min_level": 25,
      "max_level": 55,
      "experience": 0,
      "display_names": [
        "Dread Templar"
      ],
      "costumes": [
        "BK_DreadTemplar_01",
        "BK_DreadTemplar_02",
        "BK_DreadTemplar_03"
      ]
    }
  ]
}
