{
  "name": "GenericHeroes_LeoKnight_Boss_NoXP",
  "gender": "GENDER_MALE",
  "group_name": "GenericHeroes",
  "commandable_pet": 0,
  "power_tags": [
    "Humanoid",
    "HumanSkeleton"
  ],
  "ally": "Hero",
  "gang": null,
  "game_exclusion": "None",
  "inactive_state_weapon": null,
  "copy_creator_mods": false,
  "can_zone": false,
  "custom_badge_stat": null,
  "badge_stat_flags": "DefaultBadgeStat",
  "defaults": {
    "min_level": 20,
    "max_level": 33,
    "requires": "",
    "spawn_limit": -1,
    "spawn_limit_mission": -1,
    "ignore_combat_mods": false,
    "ignore_av_to_eb_scaling": false,
    "rank": "VR_BOSS",
    "ai_config": "Default_Melee",
    "character_class_name": "boss_grunt",
    "description": "This massive Tanker is the older brother of Longbow Agent Caspian. The same Caspian you captured for Vargas. He's angry, he's tough, and beating the villain who caught his little brother is his top priority.",
    "group_description": "Longbow",
    "display_class_name": null,
    "display_name": null,
    "costume": null,
    "reward_scale": 0.0,
    "additional_rewards": [],
    "power_full_names": [
      "V_GenericHeroes.SS_Tanker.Jab",
      "V_GenericHeroes.SS_Tanker.Punch",
      "V_GenericHeroes.SS_Tanker.Hurl",
      "V_GenericHeroes.SS_Tanker.Temp_Invulnerability",
      "V_GenericHeroes.SS_Tanker.Resistance",
      "V_GenericHeroes.SS_Tanker_Low.Haymaker",
      "V_GenericHeroes.SS_Tanker_Low.Hand_Clap",
      "V_GenericHeroes.SS_Tanker_Low.Unyielding"
    ],
    "power_display_names": [
      "Jab",
      "Punch",
      "Hurl",
      "Temp Invulnerability",
      "Resistance",
      "Haymaker",
      "Hand Clap",
      "Unyielding"
    ],
    "power_levels": [
      0,
      0,
      0,
      0,
      0,
      0,
      0,
      0
    ],
    "is_dynamic": false,
    "powers": [
      {
        "power_category": "V_GenericHeroes",
        "power_set": "SS_Tanker",
        "power": "*",
        "level": 0
      },
      {
        "power_category": "V_GenericHeroes",
        "power_set": "SS_Tanker_Low",
        "power": "*",
        "level": 0
      }
    ],
    "condition_hash": null
  },
  "conditions": [],
  "levels": [
    {
      "min_level": 20,
      "max_level": 33,
      "experience": 0,
      "display_names": [
        "LeoKnight"
      ],
      "costumes": [
        "Model_Leo_Knight"
      ]
    }
  ]
}
