{
  "name": "MaltaEndgame_Hercules_Titan",
  "gender": "GENDER_MALE",
  "group_name": "MaltaEndgame",
  "commandable_pet": 0,
  "power_tags": [
    "Electronic"
  ],
  "ally": null,
  "gang": null,
  "game_exclusion": "None",
  "inactive_state_weapon": null,
  "copy_creator_mods": false,
  "can_zone": false,
  "custom_badge_stat": null,
  "badge_stat_flags": "DefaultBadgeStat",
  "defaults": {
    "min_level": 50,
    "max_level": 60,
    "requires": "",
    "spawn_limit": -1,
    "spawn_limit_mission": -1,
    "ignore_combat_mods": false,
    "ignore_av_to_eb_scaling": false,
    "rank": "VR_LIEUTENANT",
    "ai_config": "Malta_Hercules_Titan",
    "character_class_name": "lt_praetoriangrunt",
    "description": "The Hercules class is the smallest Titan unit employed by Malta. It is believed that the technology used to create them came to this covert villain group sometime during or after the fall of the Soviet Union. It has not yet been determined if the Titans are simply robots, or something more. Their offensive capabilities are many and varied.",
    "group_description": null,
    "display_class_name": null,
    "display_name": null,
    "costume": null,
    "reward_scale": 1.0,
    "additional_rewards": [],
    "power_full_names": [
      "Malta.Malta_Hercules.Resistance",
      "Malta.Malta_Hercules.Merge",
      "Malta.Malta_Hercules.Pummel",
      "Malta.Malta_Hercules.Plasma_Blast",
      "Malta.Malta_Hercules.Swarm_Missile",
      "Malta.Malta_Hercules.Incendiary_Swarm_Missiles",
      "Malta.Malta_Hercules.Gas_Swarm_Missiles"
    ],
    "power_display_names": [
      "Resistance",
      "Merge",
      "Pummel",
      "Plasma Blast",
      "Swarm Missile",
      "Incendiary Swarm Missiles",
      "Gas Swarm Missiles"
    ],
    "power_levels": [
      0,
      0,
      0,
      0,
      0,
      0,
      0
    ],
    "is_dynamic": false,
    "powers": [
      {
        "power_category": "Malta",
        "power_set": "Malta_Hercules",
        "power": "*",
        "level": 0
      }
    ],
    "condition_hash": null
  },
  "conditions": [],
  "levels": [
    {
      "min_level": 50,
      "max_level": 60,
      "experience": 0,
      "display_names": [
        "Hercules Class Titan"
      ],
      "costumes": [
        "Malta_Hercules_Titan_01"
      ]
    }
  ]
}
