{
  "name": "TalonsOfVengeance_Gorgon_Boss",
  "gender": "GENDER_FEMALE",
  "group_name": "TalonsOfVengeance",
  "commandable_pet": 0,
  "power_tags": [
    "HumanSkeleton",
    "Human"
  ],
  "ally": null,
  "gang": null,
  "game_exclusion": "None",
  "inactive_state_weapon": null,
  "copy_creator_mods": false,
  "can_zone": false,
  "custom_badge_stat": "kills.TalonsOfVengeance_Gorgon",
  "badge_stat_flags": "DefaultBadgeStat",
  "defaults": {
    "min_level": 25,
    "max_level": 34,
    "requires": "",
    "spawn_limit": 0,
    "spawn_limit_mission": 0,
    "ignore_combat_mods": false,
    "ignore_av_to_eb_scaling": false,
    "rank": "VR_BOSS",
    "ai_config": "Default_Melee",
    "character_class_name": "boss_grunt",
    "description": "The Gorgons are among the most monstrous members of the Talons of Vengeance. They are fully transformed hybrids between woman and serpent, with almost no trace of the person they once were emerging from their hideous faces. They are extremely powerful swordswomen, capable of cutting through their enemies with speed and precision. Worse still, they make full use of their terrifying appearance to control their enemies, even to the point of turning them to stone.",
    "group_description": null,
    "display_class_name": null,
    "display_name": null,
    "costume": null,
    "reward_scale": 1.0,
    "additional_rewards": [],
    "power_full_names": [
      "TalonsOfVengeance.Gorgon.Slash",
      "TalonsOfVengeance.Gorgon.Hack",
      "TalonsOfVengeance.Gorgon.Savage_Slice",
      "TalonsOfVengeance.Gorgon.Savage_Strike",
      "TalonsOfVengeance.Gorgon.Throwing_Knives",
      "TalonsOfVengeance.Gorgon.Sirens_Song",
      "TalonsOfVengeance.Resistances.Damage_BS"
    ],
    "power_display_names": [
      "Slash",
      "Hack",
      "Savage Slice",
      "Savage Strike",
      "Throwing Knives",
      "Siren's Song",
      "Damage Resistance"
    ],
    "power_levels": [
      0,
      0,
      0,
      0,
      0,
      0,
      0
    ],
    "is_dynamic": false,
    "powers": [
      {
        "power_category": "TalonsOfVengeance",
        "power_set": "Gorgon",
        "power": "Slash",
        "level": 0
      },
      {
        "power_category": "TalonsOfVengeance",
        "power_set": "Gorgon",
        "power": "Hack",
        "level": 0
      },
      {
        "power_category": "TalonsOfVengeance",
        "power_set": "Gorgon",
        "power": "Savage_Slice",
        "level": 0
      },
      {
        "power_category": "TalonsOfVengeance",
        "power_set": "Gorgon",
        "power": "Savage_Strike",
        "level": 0
      },
      {
        "power_category": "TalonsOfVengeance",
        "power_set": "Gorgon",
        "power": "Throwing_Knives",
        "level": 0
      },
      {
        "power_category": "TalonsOfVengeance",
        "power_set": "Gorgon",
        "power": "Sirens_Song",
        "level": 0
      },
      {
        "power_category": "TalonsOfVengeance",
        "power_set": "Resistances",
        "power": "Damage_BS",
        "level": 0
      }
    ],
    "condition_hash": null
  },
  "conditions": [],
  "levels": [
    {
      "min_level": 25,
      "max_level": 34,
      "experience": 0,
      "display_names": [
        "Gorgon"
      ],
      "costumes": [
        "Talons_Gorgon_01",
        "Talons_Gorgon_02"
      ]
    }
  ]
}
