{
  "name": "Upstart_Melee",
  "display_name": "Upstart_Melee",
  "display_fullname": "Freakshow.Upstart Melee",
  "display_help": "Upstart_Melee",
  "display_short_help": "Upstart_Melee",
  "available_level": [
    0,
    0,
    7,
    0,
    15
  ],
  "source_file": "DEFS/POWERS/FREAKSHOW/UPSTART_MELEE.POWERSETS",
  "icon": "macro_button_01.png",
  "requires": "",
  "power_names": [
    "Freakshow.Upstart_Melee.Initial_Strike",
    "Freakshow.Upstart_Melee.Heavy_Blow",
    "Freakshow.Upstart_Melee.Throat_Strike",
    "Freakshow.Upstart_Melee.Cybernetic_Blade",
    "Freakshow.Upstart_Melee.Spot_Prey"
  ],
  "power_display_names": [
    "Initial Strike",
    "Heavy Blow",
    "Rib Cracker",
    "Cybernetic Blade",
    "Spot Prey"
  ],
  "power_short_helps": [
    "Melee, Light DMG (Smash), Foe Disorient, Combo Builder",
    "Melee, Moderate DMG (Smash), Foe Knockdown, Combo Builder",
    "Melee, Moderate DMG (Smash), Foe -Res (All), -Dmg, Combo Builder",
    "Melee Lethal",
    "Self +To Hit, +DMG, +Perception"
  ]
}
