{
  "name": "Crafted_Thunderstrike_C",
  "display_name": "Crafted Thunderstrike C",
  "display_fullname": "Boosts.Crafted Thunderstrike C",
  "display_help": "Enhances the damage of a power by {Boost.Attrib.Damage.Scale}% and reduces recharge time by {Boost.Attrib.RechargeTime.Scale}%.",
  "display_short_help": "Set: Thunderstrike",
  "available_level": [
    0
  ],
  "source_file": "DEFS/POWERS/BOOSTS/CRAFTED_THUNDERSTRIKE_C.POWERSETS",
  "icon": "crafted_thunderstrike_c_set.png",
  "requires": "",
  "power_names": [
    "Boosts.Crafted_Thunderstrike_C.Crafted_Thunderstrike_C"
  ],
  "power_display_names": [
    "Thunderstrike: Damage/Recharge"
  ],
  "power_short_helps": [
    "Enhances Damage and Recharge"
  ]
}
