{
  "name": "Science_Intangible",
  "display_name": "Science Intangible",
  "display_fullname": "Boosts.Science Intangible",
  "display_help": "Increases the duration of an intangibility power.",
  "display_short_help": "Experiment (Science)",
  "available_level": [
    0
  ],
  "source_file": "DEFS/POWERS/BOOSTS/SCIENCE_INTANGIBLE.POWERSETS",
  "icon": "science_intangible_set.png",
  "requires": "",
  "power_names": [
    "Boosts.Science_Intangible.Science_Intangible"
  ],
  "power_display_names": [
    "Hydrazine Exposure (Intangible)"
  ],
  "power_short_helps": [
    "Enhances Intangibility Duration"
  ]
}
