{
  "name": "Hero3",
  "display_name": "Hero3",
  "display_fullname": "DevouringEarth.Hero3",
  "display_help": "Devouring Earth Crystal ranged powers.",
  "display_short_help": "Devouring Earth Crystal ranged powers.",
  "available_level": [
    0,
    0,
    0,
    0,
    0,
    0,
    0,
    0,
    0,
    0,
    0
  ],
  "source_file": "DEFS/POWERS/DEVOURINGEARTH/HERO3.POWERSETS",
  "icon": "hero3_set.png",
  "requires": "",
  "power_names": [
    "DevouringEarth.Hero3.Charged_Bolts",
    "DevouringEarth.Hero3.Gale",
    "DevouringEarth.Hero3.Lightning_Bolt",
    "DevouringEarth.Hero3.Ball_Lightning",
    "DevouringEarth.Hero3.Havoc_Punch",
    "DevouringEarth.Hero3.Thunder_Strike",
    "DevouringEarth.Hero3.Thunder_Clap",
    "DevouringEarth.Hero3.Freezing_Rain",
    "DevouringEarth.Hero3.Hurricane",
    "DevouringEarth.Hero3.Lightning_Storm",
    "DevouringEarth.Hero3.SummonFX"
  ],
  "power_display_names": [
    "Charged Bolts",
    "Gale",
    "Lightning Bolt",
    "Ball Lightning",
    "Havoc Punch",
    "Thunder Strike",
    "Thunder Clap",
    "Freezing Rain",
    "Hurricane",
    "Lightning Storm",
    "SummonFX"
  ],
  "power_short_helps": [
    "Ranged Energy, -End",
    "Ranged (Cone), Minor DMG(Smash), Foe Knockback",
    "Ranged Energy, -End",
    "Targeted AoE Energy, -End",
    "Sleep",
    "Disorient",
    "AoE Stun",
    "DoT(Cold), -Speed, -Recharge, -DEF, -Res",
    "-Range, -ACC, Knockback",
    "Summon Lightning Storm",
    "Summon"
  ]
}
