{
  "name": "Attuned_Quickfoot_C",
  "display_name": "Attuned Quickfoot C",
  "display_fullname": "Boosts.Attuned Quickfoot C",
  "display_help": "Enhances the run speed of a power by {Boost.Attrib.Movement.Scale}% and reduces the endurance cost of a power by {Boost.Attrib.Endurance.Scale}%.",
  "display_short_help": "Set: Quickfoot",
  "available_level": [
    0
  ],
  "source_file": "DEFS/POWERS/BOOSTS/ATTUNED_QUICKFOOT_C.POWERSETS",
  "icon": "attuned_quickfoot_c_set.png",
  "requires": "",
  "power_names": [
    "Boosts.Attuned_Quickfoot_C.Attuned_Quickfoot_C"
  ],
  "power_display_names": [
    "Quickfoot: Endurance/Run"
  ],
  "power_short_helps": [
    "+Run, -End Cost"
  ]
}
