{
  "name": "Dominator_DarkAssault_Snipe",
  "display_name": "Dominator_DarkAssault_Snipe",
  "display_fullname": "Villain Pets.Dominator DarkAssault Snipe",
  "display_help": "Dark Assault",
  "display_short_help": "Dark Assault",
  "available_level": [
    27,
    27
  ],
  "source_file": "DEFS/POWERS/VILLAIN_PETS/DOMINATOR_DARKASSAULT_SNIPE.POWERSETS",
  "icon": "dominator_darkassault_snipe_set.png",
  "requires": "",
  "power_names": [
    "Villain_Pets.Dominator_DarkAssault_Snipe.Death_Shroud_Quick",
    "Villain_Pets.Dominator_DarkAssault_Snipe.Death_Shroud_Normal"
  ],
  "power_display_names": [
    "Moon Beam",
    "Moon Beam"
  ],
  "power_short_helps": [
    "Sniper, Extreme DMG(Negative), Target -To Hit",
    "Sniper, Extreme DMG(Negative), Target -To Hit"
  ]
}
