{
  "name": "Warcry",
  "display_name": "Warcry",
  "display_fullname": "Council.Warcry",
  "display_help": "Council",
  "display_short_help": "Council",
  "available_level": [
    0,
    0,
    0,
    0
  ],
  "source_file": "DEFS/POWERS/COUNCIL/WARCRY.POWERSETS",
  "icon": "warcry_set.png",
  "requires": "",
  "power_names": [
    "Council.Warcry.Power_Blast",
    "Council.Warcry.Missile_Launch",
    "Council.Warcry.Pummel",
    "Council.Warcry.Resistance"
  ],
  "power_display_names": [
    "Power Blast",
    "Missile Launch",
    "Pummel",
    "Resistance"
  ],
  "power_short_helps": [
    "Ranged, Heavy DMG(Energy/Smash), Foe Knockback",
    "Ranged (Targeted AoE), Superior DMG(Fire/Lethal), Foe Knockback",
    "Melee, Heavy DMG(Smash), Foe Knockback",
    "Auto Res KB"
  ]
}
