{
  "name": "Attuned_Horror_B",
  "display_name": "Attuned Horror B",
  "display_fullname": "Boosts.Attuned Horror B",
  "display_help": "Enhances the fear duration of a power by {Boost.Attrib.Mez.Scale}% and reduces the endurance cost of a power by {Boost.Attrib.Endurance.Scale}%.",
  "display_short_help": "Set: Horror",
  "available_level": [
    0
  ],
  "source_file": "DEFS/POWERS/BOOSTS/ATTUNED_HORROR_B.POWERSETS",
  "icon": "attuned_horror_b_set.png",
  "requires": "",
  "power_names": [
    "Boosts.Attuned_Horror_B.Attuned_Horror_B"
  ],
  "power_display_names": [
    "Horror: Endurance/Fear"
  ],
  "power_short_helps": [
    "-End Cost, +Fear"
  ]
}
