{
  "name": "CouncilEmpire",
  "display_name": "CouncilEmpire",
  "source_file": "DEFS/POWERS/COUNCILEMPIRE.CATEGORIES",
  "archetypes": [],
  "display_help": null,
  "display_short_help": null,
  "powerset_names": [
    "councilempire.bossgrenadelauncher",
    "councilempire.bossmissilelauncher",
    "councilempire.chaingun",
    "councilempire.flamethrower",
    "councilempire.grenade",
    "councilempire.lt_boss_solider_ranged",
    "councilempire.martialarts",
    "councilempire.melee",
    "councilempire.missile",
    "councilempire.rifle"
  ],
  "powerset_display_names": [
    "Grenade Launcher",
    "Missile Launcher",
    "ChainGun",
    "Flamethrower",
    "Grenade",
    "Lt Boss Solider Ranged",
    "MartialArts",
    "Melee",
    "Missile",
    "Rifle"
  ],
  "powersets_with_requirements": []
}
