{
  "name": "Malta_Hercules",
  "display_name": "Malta_Hercules",
  "display_fullname": "Malta.Malta Hercules",
  "display_help": "Malta Group",
  "display_short_help": "Malta Group",
  "available_level": [
    0,
    0,
    0,
    0,
    0,
    0,
    0
  ],
  "source_file": "DEFS/POWERS/MALTA/MALTA_HERCULES.POWERSETS",
  "icon": "malta_hercules_set.png",
  "requires": "",
  "power_names": [
    "Malta.Malta_Hercules.Resistance",
    "Malta.Malta_Hercules.Merge",
    "Malta.Malta_Hercules.Pummel",
    "Malta.Malta_Hercules.Plasma_Blast",
    "Malta.Malta_Hercules.Swarm_Missile",
    "Malta.Malta_Hercules.Incendiary_Swarm_Missiles",
    "Malta.Malta_Hercules.Gas_Swarm_Missiles"
  ],
  "power_display_names": [
    "Resistance",
    "Merge",
    "Pummel",
    "Plasma Blast",
    "Swarm Missile",
    "Incendiary Swarm Missiles",
    "Gas Swarm Missiles"
  ],
  "power_short_helps": [
    "Self Auto, Res(All), Res Sleep, Fear",
    "Merge",
    "Melee (Cone) Heavy Smash",
    "-Regeneration",
    "Ranged AoE Lethal, +KB",
    "Ranged AoE Lethal, +Burn",
    "Ranged AoE Lethal, +Hold"
  ]
}
