{
  "name": "Dark_Miasma",
  "display_name": "Dark Miasma",
  "display_fullname": "Redirects.Dark Miasma",
  "display_help": "These powers are used by Dark Miasma powers.",
  "display_short_help": "Tanker Melee",
  "available_level": [
    0,
    0,
    0
  ],
  "source_file": "DEFS/POWERS/REDIRECTS/DARK_MIASMA.POWERSETS",
  "icon": "tanker_melee_set.png",
  "requires": "",
  "power_names": [
    "Redirects.Dark_Miasma.Twilight",
    "Redirects.Dark_Miasma.Tar",
    "Redirects.Dark_Miasma.Tar_Epic"
  ],
  "power_display_names": [
    "Twilight Grasp",
    "Tar",
    "Tar"
  ],
  "power_short_helps": [
    "Twilight",
    "Ranged (Location AoE), Target -Speed, -Res, -Fly",
    "Ranged (Location AoE), Target -Speed, -Res, -Fly"
  ]
}
