{
  "name": "Crey_Boss_Armored_Buff_High",
  "display_name": "Crey_Boss_Armored_Buff_High",
  "display_fullname": "Crey.Crey Boss Armored Buff High",
  "display_help": "Crey",
  "display_short_help": "Crey",
  "available_level": [
    0,
    1
  ],
  "source_file": "DEFS/POWERS/CREY/CREY_BOSS_ARMORED_BUFF_HIGH.POWERSETS",
  "icon": "crey_boss_armored_buff_set.png",
  "requires": "",
  "power_names": [
    "Crey.Crey_Boss_Armored_Buff_High.Deflection_Shield",
    "Crey.Crey_Boss_Armored_Buff_High.Force_Bolt"
  ],
  "power_display_names": [
    "Deflection Shield",
    "Force Bolt"
  ],
  "power_short_helps": [
    "Ranged, Ally +DEF(Smash, Lethal, Fire, Cold, Energy, Negative), +Res(Toxic, End Drain)",
    "Ranged, Minor DMG(Smash), Foe Knockback"
  ]
}
