{
  "name": "Citizen_Minion_Serious",
  "display_name": "Citizen_Minion_Serious",
  "display_fullname": "P Citizens.Citizen Minion Serious",
  "display_help": "Citizens",
  "display_short_help": "Citizens",
  "available_level": [
    0,
    0
  ],
  "source_file": "DEFS/POWERS/P_CITIZENS/CITIZEN_MINION_SERIOUS.POWERSETS",
  "icon": "citizen_minion_serious_set.png",
  "requires": "",
  "power_names": [
    "P_Citizens.Citizen_Minion_Serious.Rock",
    "P_Citizens.Citizen_Minion_Serious.Brawl"
  ],
  "power_display_names": [
    "Rock",
    "Brawl"
  ],
  "power_short_helps": [
    "Ranged Smash",
    "Melee Smash"
  ]
}
