{
  "name": "Commando_2",
  "display_name": "Mercenary Commando 2",
  "display_fullname": "Mastermind Pets.Mercenary Commando 2",
  "display_help": "Mercenaries",
  "display_short_help": "Mercenaries",
  "available_level": [
    0,
    0,
    0,
    0
  ],
  "source_file": "DEFS/POWERS/MASTERMIND_PETS/COMMANDO_2.POWERSETS",
  "icon": "commando_2_set.png",
  "requires": "",
  "power_names": [
    "Mastermind_Pets.Commando_2.Heavy_Burst",
    "Mastermind_Pets.Commando_2.Buckshot",
    "Mastermind_Pets.Commando_2.Full_Auto",
    "Mastermind_Pets.Commando_2.Equip"
  ],
  "power_display_names": [
    "Heavy Burst",
    "Buckshot",
    "Full Auto",
    "Equip"
  ],
  "power_short_helps": [
    "-Def",
    "Ranged (Cone), DMG(Lethal), Foe Knockback",
    "Ranged (Cone), DMG(Lethal), +Special",
    "Equip"
  ]
}
