{
  "name": "DualBlade_MN",
  "display_name": "DualBlade_MN",
  "display_fullname": "KnivesOfVengeance.DualBlade MN",
  "display_help": "Knives of Vengeance",
  "display_short_help": "Knives of Vengeance",
  "available_level": [
    0,
    0,
    0,
    0
  ],
  "source_file": "DEFS/POWERS/KNIVESOFVENGEANCE/DUALBLADE_MN.POWERSETS",
  "icon": "dualblade_mn_set.png",
  "requires": "",
  "power_names": [
    "KnivesOfVengeance.DualBlade_MN.Deft_Slash",
    "KnivesOfVengeance.DualBlade_MN.Deft_Slice",
    "KnivesOfVengeance.DualBlade_MN.Shearing_Strike",
    "KnivesOfVengeance.DualBlade_MN.Shockwave_Slice"
  ],
  "power_display_names": [
    "Deft Slash",
    "Deft Slice",
    "Shearing Strike",
    "Shockwave Slice"
  ],
  "power_short_helps": [
    "Melee, Minor DMG(Lethal), Minor DoT (Lethal)",
    "Melee, Moderate DMG(Lethal), Moderate DoT (Lethal), Knockdown (Foe)",
    "Melee, High DMG (Lethal), High DoT (Lethal), -DEF(Foe,All), -ToHit(Foe)",
    "Ranged (Cone), High DMG(Lethal), Moderate DoT (Lethal), Chance for -Speed(All), -Recharge on Foes"
  ]
}
