{
  "name": "Black_Whip",
  "display_name": "Black_Whip",
  "display_fullname": "Event.Black Whip",
  "display_help": "Halloween",
  "display_short_help": "Halloween",
  "available_level": [
    0,
    0,
    0,
    0,
    0,
    0,
    0,
    0,
    0,
    0,
    0,
    0,
    0,
    0
  ],
  "source_file": "DEFS/POWERS/EVENT/BLACK_WHIP.POWERSETS",
  "icon": "macro_button_01.png",
  "requires": "",
  "power_names": [
    "Event.Black_Whip.Scream",
    "Event.Black_Whip.Shout",
    "Event.Black_Whip.Howl",
    "Event.Black_Whip.Shockwave",
    "Event.Black_Whip.Sonic_Dispersion",
    "Event.Black_Whip.Sonic_Barrier",
    "Event.Black_Whip.Screech",
    "Event.Black_Whip.Crack_Whip",
    "Event.Black_Whip.Lash",
    "Event.Black_Whip.Corruption",
    "Event.Black_Whip.Summon_Demonlings",
    "Event.Black_Whip.Summon_Demons",
    "Event.Black_Whip.Summon_Demon_Prince",
    "Event.Black_Whip.Hell_on_Earth"
  ],
  "power_display_names": [
    "Scream",
    "Shout",
    "Howl",
    "Shockwave",
    "Sonic Dispersion",
    "Sonic Barrier",
    "Screech",
    "Crack Whip",
    "Lash",
    "Corruption",
    "Summon Demonlings",
    "Summon Demons",
    "Summon Demon Prince",
    "Hell on Earth"
  ],
  "power_short_helps": [
    "Ranged, Moderate DoT(Smashing/Energy), -Resist",
    "Ranged, Heavy DMG(Smashing/Energy), Foe -Res(All)",
    "Ranged Cone, Medium DMG(Smashing/Energy)",
    "Ranged (Cone), Minor DMG(Smashing/Energy), Foe Knockback",
    "Toggle: PBAoE, Ally +Res(All Damage, Hold, Immobilize, Disorient)",
    "Ranged, Ally +Res(Smash, Lethal, Toxic)",
    "Ranged, Minor Damage (Smashing/Energy), Foe Disorient, -Res(All)",
    "Short Ranged (Cone), High DMG(Fire), Foe -Res, Knockdown, DoT(Toxic)",
    "Close, High DMG(Fire), Foe -Res, Knockdown, Minor DoT(Toxic)",
    "Ranged, Minor DMG(Fire), Foe Minor DoT (Toxic), -Res",
    "Summon Demonlings",
    "Summon Demons",
    "Summon Demon Prince",
    "Ranged, Pet +Dmg, +To Hit, Summon Living Hellfire"
  ]
}
