{
  "name": "Crafted_Immobilize_45",
  "display_name": "Crafted Immobilize 45",
  "display_fullname": "Boosts.Crafted Immobilize 45",
  "display_help": "Increases immobilization duration by {Boost.Attrib.Mez.Scale}%.",
  "display_short_help": "Invention",
  "available_level": [
    0
  ],
  "source_file": "DEFS/POWERS/BOOSTS/CRAFTED_IMMOBILIZE_45.POWERSETS",
  "icon": "crafted_immobilize_45_set.png",
  "requires": "",
  "power_names": [
    "Boosts.Crafted_Immobilize_45.Crafted_Immobilize_45"
  ],
  "power_display_names": [
    "Invention: Immobilization Duration"
  ],
  "power_short_helps": [
    "Enhances Immobilization Duration"
  ]
}
