{
  "name": "Tuatha_Minion_Melee",
  "display_name": "Tuatha_Adept_Minion_Melee",
  "display_fullname": "Tuatha.Tuatha Adept Minion Melee",
  "display_help": "The Tuatha",
  "display_short_help": "The Tuatha",
  "available_level": [
    0,
    0
  ],
  "source_file": "DEFS/POWERS/TUATHA/TUATHA_MINION_MELEE.POWERSETS",
  "icon": "tuatha_minion_melee_set.png",
  "requires": "",
  "power_names": [
    "Tuatha.Tuatha_Minion_Melee.Smash",
    "Tuatha.Tuatha_Minion_Melee.Head_Butt"
  ],
  "power_display_names": [
    "Smash",
    "Head Butt"
  ],
  "power_short_helps": [
    "Melee Smashing",
    "Melee Smashing"
  ]
}
