{
  "name": "Clockwork_Soldier_A",
  "display_name": "Clockwork Soldier A",
  "display_fullname": "NewPraetorians.Clockwork Soldier A",
  "display_help": "Clockwork",
  "display_short_help": "Clockwork",
  "available_level": [
    0,
    0
  ],
  "source_file": "DEFS/POWERS/NEWPRAETORIANS/CLOCKWORK_SOLDIER_A.POWERSETS",
  "icon": "clockwork_soldier_a_set.png",
  "requires": "",
  "power_names": [
    "NewPraetorians.Clockwork_Soldier_A.Plasma_Blast",
    "NewPraetorians.Clockwork_Soldier_A.Plasma_Ray"
  ],
  "power_display_names": [
    "Plasma Blast",
    "Plasma Ray"
  ],
  "power_short_helps": [
    "Ranged, High DoT (Energy), Foe -Regen",
    "Ranged (Narrow Cone), High DMG(Energy) -Rec (Foe)"
  ]
}
